drz/__init__.py
drz/cli.py
drz-0.1.dist-info/LICENSE
drz-0.1.dist-info/METADATA
drz-0.1.dist-info/WHEEL
drz-0.1.dist-info/entry_points.txt
drz-0.1.dist-info/top_level.txt
drz-0.1.dist-info/RECORD
