Metadata-Version: 2.1
Name: drz
Version: 0.1
Summary: A painless deployment system for modern code
Home-page: https://github.com/kilometercreative/Drizzle
Author: Kaeden Wile
Author-email: kaeden@kilometercreative.com
License: MIT
Platform: UNKNOWN
